{
  "batch_id": "v8_defocus_difference_features",
  "run_id": "v8_defocus_difference_features_20260614_000621_utc",
  "created_utc": "2026-06-14T03:30:58.210945+00:00",
  "status": "complete",
  "batch_config": "colab_worker_logs/model_selection_batch_v8_defocus_difference_features_runtime.json",
  "max_runtime_minutes": 230.0,
  "estimated_minutes_per_job": 30.0,
  "walltime_safety_margin_minutes": 12.0,
  "jobs": [
    {
      "job_id": "v8_fixedsplit_d66_seed23",
      "candidate_id": "D66_grouped_width320_lr6e-4_dropout0.075_v8fixedsplit_d66_seed23",
      "status": "skipped_completed",
      "selection_score_path": "training_results/model_selection_loop/D66_grouped_width320_lr6e-4_dropout0.075_v8fixedsplit_d66_seed23_20260613_231756_utc/selection_score.json",
      "weighted_score": 0.0366377102318578,
      "rejected": false,
      "true_hard_target_normalized_mae": 0.018527092412114143,
      "hard_label_normalized_mae": 0.018090681817669138,
      "hard_label_normalized_p95": 0.0634470393594641,
      "overall_normalized_mae": 0.013985180296003819,
      "overall_normalized_p95": 0.052456844598054886,
      "easy_target_normalized_mae_relative_change": 0.005673837371338457,
      "C1_mae": 0.8919318914413452,
      "C1_rmse": 1.4713737964630127,
      "C1_p95_abs_error": 3.1141109466552734,
      "C1_bias": 0.0553165078163147,
      "C1_normalized_mae": 0.00891931913793087,
      "C1_normalized_p95_abs_error": 0.031141109764575958,
      "validation_normalized_mae": 0.013985180296003819,
      "validation_C1_mae": 1.792754888534546,
      "validation_C1_rmse": 2.914816379547119,
      "validation_C1_p95_abs_error": 5.8765997886657715,
      "validation_C1_bias": 0.2292623072862625,
      "validation_C1_normalized_mae": 0.01792754977941513,
      "validation_C1_normalized_p95_abs_error": 0.058765996247529984,
      "blind_normalized_mae": 0.010960858315229416,
      "blind_C1_mae": 1.2718461751937866,
      "blind_C1_rmse": 2.0584261417388916,
      "blind_C1_p95_abs_error": 4.209012031555176,
      "blind_C1_bias": 0.18860949575901031,
      "blind_C1_normalized_mae": 0.012718461453914642,
      "blind_C1_normalized_p95_abs_error": 0.042090121656656265,
      "stress_normalized_mae": 0.010209410451352596,
      "stress_C1_mae": 1.2097731828689575,
      "stress_C1_rmse": 2.321133852005005,
      "stress_C1_p95_abs_error": 4.987336158752441,
      "stress_C1_bias": 0.028153609484434128,
      "stress_C1_normalized_mae": 0.012097732163965702,
      "stress_C1_normalized_p95_abs_error": 0.049873363226652145,
      "S3_high_magnitude_mae": 6.109638690948486,
      "S3_high_magnitude_bias": -4.443100929260254,
      "S3_high_magnitude_slope": 0.812416315788721,
      "S3_high_mean_abs_angle_error_deg": 2.917630910873413,
      "S3_high_p95_abs_angle_error_deg": 8.974971771240234,
      "B2_magnitude_mae": 0.06352008879184723,
      "B2_mean_abs_angle_error_deg": 3.1767702102661133,
      "A3_magnitude_mae": 1.3807569742202759,
      "A3_mean_abs_angle_error_deg": 2.5268869400024414
    },
    {
      "job_id": "v8_c1diff_basic_seed23",
      "candidate_id": "D66_grouped_width320_lr6e-4_dropout0.075_v8c1diff_basic_seed23",
      "status": "complete",
      "returncode": 0,
      "elapsed_minutes": 55.76969778621666,
      "selection_score_path": "training_results/model_selection_loop/D66_grouped_width320_lr6e-4_dropout0.075_v8c1diff_basic_seed23_20260614_000621_utc/selection_score.json",
      "weighted_score": 0.03779580818489194,
      "rejected": false,
      "true_hard_target_normalized_mae": 0.018852335400879383,
      "hard_label_normalized_mae": 0.018374078083210267,
      "hard_label_normalized_p95": 0.06513733982753295,
      "overall_normalized_mae": 0.014134794473648071,
      "overall_normalized_p95": 0.052974265068769455,
      "easy_target_normalized_mae_relative_change": 0.007936291717240843,
      "C1_mae": 0.8720908164978027,
      "C1_rmse": 1.4446476697921753,
      "C1_p95_abs_error": 3.025003433227539,
      "C1_bias": 0.10605595260858536,
      "C1_normalized_mae": 0.00872090831398964,
      "C1_normalized_p95_abs_error": 0.030250035226345062,
      "validation_normalized_mae": 0.014134794473648071,
      "validation_C1_mae": 1.75738525390625,
      "validation_C1_rmse": 2.8514041900634766,
      "validation_C1_p95_abs_error": 5.805047988891602,
      "validation_C1_bias": 0.25398027896881104,
      "validation_C1_normalized_mae": 0.017573852092027664,
      "validation_C1_normalized_p95_abs_error": 0.058050479739904404,
      "blind_normalized_mae": 0.011150702834129333,
      "blind_C1_mae": 1.2479521036148071,
      "blind_C1_rmse": 1.9900215864181519,
      "blind_C1_p95_abs_error": 4.189547538757324,
      "blind_C1_bias": 0.23905257880687714,
      "blind_C1_normalized_mae": 0.012479521334171295,
      "blind_C1_normalized_p95_abs_error": 0.04189547523856163,
      "stress_normalized_mae": 0.010409494861960411,
      "stress_C1_mae": 1.2148882150650024,
      "stress_C1_rmse": 2.3414652347564697,
      "stress_C1_p95_abs_error": 5.068765640258789,
      "stress_C1_bias": 0.12148561328649521,
      "stress_C1_normalized_mae": 0.012148882262408733,
      "stress_C1_normalized_p95_abs_error": 0.05068765580654144,
      "S3_high_magnitude_mae": 6.020186901092529,
      "S3_high_magnitude_bias": -4.385275363922119,
      "S3_high_magnitude_slope": 0.8254445932980597,
      "S3_high_mean_abs_angle_error_deg": 3.0997297763824463,
      "S3_high_p95_abs_angle_error_deg": 10.557927131652832,
      "B2_magnitude_mae": 0.060853131115436554,
      "B2_mean_abs_angle_error_deg": 3.413386344909668,
      "A3_magnitude_mae": 1.4294356107711792,
      "A3_mean_abs_angle_error_deg": 2.6038858890533447
    },
    {
      "job_id": "v8_c1diff_full_seed23",
      "candidate_id": "D66_grouped_width320_lr6e-4_dropout0.075_v8c1diff_full_seed23",
      "status": "complete",
      "returncode": 0,
      "elapsed_minutes": 57.76682957346666,
      "selection_score_path": "training_results/model_selection_loop/D66_grouped_width320_lr6e-4_dropout0.075_v8c1diff_full_seed23_20260614_010207_utc/selection_score.json",
      "weighted_score": 0.036357190888016845,
      "rejected": false,
      "true_hard_target_normalized_mae": 0.01813179850578308,
      "hard_label_normalized_mae": 0.01805195242811281,
      "hard_label_normalized_p95": 0.0636647421006973,
      "overall_normalized_mae": 0.01381741277873516,
      "overall_normalized_p95": 0.051756687462329865,
      "easy_target_normalized_mae_relative_change": 0.005182088023625179,
      "C1_mae": 0.8130364418029785,
      "C1_rmse": 1.3229542970657349,
      "C1_p95_abs_error": 2.695530891418457,
      "C1_bias": -0.008511317893862724,
      "C1_normalized_mae": 0.008130364120006561,
      "C1_normalized_p95_abs_error": 0.02695530839264393,
      "validation_normalized_mae": 0.01381741277873516,
      "validation_C1_mae": 1.6778815984725952,
      "validation_C1_rmse": 2.7644009590148926,
      "validation_C1_p95_abs_error": 5.330109596252441,
      "validation_C1_bias": 0.05079377815127373,
      "validation_C1_normalized_mae": 0.016778815537691116,
      "validation_C1_normalized_p95_abs_error": 0.053301095962524414,
      "blind_normalized_mae": 0.011316279880702496,
      "blind_C1_mae": 1.242019772529602,
      "blind_C1_rmse": 2.0100228786468506,
      "blind_C1_p95_abs_error": 4.124650478363037,
      "blind_C1_bias": -0.18934234976768494,
      "blind_C1_normalized_mae": 0.012420197948813438,
      "blind_C1_normalized_p95_abs_error": 0.041246503591537476,
      "stress_normalized_mae": 0.010504192672669888,
      "stress_C1_mae": 1.2610827684402466,
      "stress_C1_rmse": 2.723520517349243,
      "stress_C1_p95_abs_error": 4.624108791351318,
      "stress_C1_bias": 0.021791653707623482,
      "stress_C1_normalized_mae": 0.012610827572643757,
      "stress_C1_normalized_p95_abs_error": 0.04624108970165253,
      "S3_high_magnitude_mae": 5.779057025909424,
      "S3_high_magnitude_bias": -4.318144798278809,
      "S3_high_magnitude_slope": 0.8288086753370688,
      "S3_high_mean_abs_angle_error_deg": 2.879251480102539,
      "S3_high_p95_abs_angle_error_deg": 10.402411460876465,
      "B2_magnitude_mae": 0.05911632254719734,
      "B2_mean_abs_angle_error_deg": 3.4314591884613037,
      "A3_magnitude_mae": 1.4851738214492798,
      "A3_mean_abs_angle_error_deg": 2.482638120651245
    },
    {
      "job_id": "v8_c1diff_basic_seed7",
      "candidate_id": "D66_grouped_width320_lr6e-4_dropout0.075_v8c1diff_basic_seed7",
      "status": "complete",
      "returncode": 0,
      "elapsed_minutes": 55.627516352883355,
      "selection_score_path": "training_results/model_selection_loop/D66_grouped_width320_lr6e-4_dropout0.075_v8c1diff_basic_seed7_20260614_015953_utc/selection_score.json",
      "weighted_score": 0.03716075346697695,
      "rejected": false,
      "true_hard_target_normalized_mae": 0.018580026179552078,
      "hard_label_normalized_mae": 0.018187590821001392,
      "hard_label_normalized_p95": 0.06350235662494713,
      "overall_normalized_mae": 0.014070942997932434,
      "overall_normalized_p95": 0.052834030240774155,
      "easy_target_normalized_mae_relative_change": 0.015899216665356687,
      "C1_mae": 0.8915224671363831,
      "C1_rmse": 1.4849849939346313,
      "C1_p95_abs_error": 3.1815667152404785,
      "C1_bias": -0.07374932616949081,
      "C1_normalized_mae": 0.00891522504389286,
      "C1_normalized_p95_abs_error": 0.03181566670536995,
      "validation_normalized_mae": 0.014070942997932434,
      "validation_C1_mae": 1.7709144353866577,
      "validation_C1_rmse": 2.850466012954712,
      "validation_C1_p95_abs_error": 5.899607181549072,
      "validation_C1_bias": -0.011438201181590557,
      "validation_C1_normalized_mae": 0.017709143459796906,
      "validation_C1_normalized_p95_abs_error": 0.05899607017636299,
      "blind_normalized_mae": 0.011013458482921124,
      "blind_C1_mae": 1.2671195268630981,
      "blind_C1_rmse": 2.029390811920166,
      "blind_C1_p95_abs_error": 4.295129776000977,
      "blind_C1_bias": -0.0025822040624916553,
      "blind_C1_normalized_mae": 0.012671194970607758,
      "blind_C1_normalized_p95_abs_error": 0.042951297014951706,
      "stress_normalized_mae": 0.010368295013904572,
      "stress_C1_mae": 1.1850665807724,
      "stress_C1_rmse": 2.37434458732605,
      "stress_C1_p95_abs_error": 5.020520210266113,
      "stress_C1_bias": -0.0599098801612854,
      "stress_C1_normalized_mae": 0.011850666254758835,
      "stress_C1_normalized_p95_abs_error": 0.05020520091056824,
      "S3_high_magnitude_mae": 6.093423366546631,
      "S3_high_magnitude_bias": -4.67245626449585,
      "S3_high_magnitude_slope": 0.8180734224680327,
      "S3_high_mean_abs_angle_error_deg": 3.137910842895508,
      "S3_high_p95_abs_angle_error_deg": 10.44970989227295,
      "B2_magnitude_mae": 0.06166098639369011,
      "B2_mean_abs_angle_error_deg": 3.4183731079101562,
      "A3_magnitude_mae": 1.4036026000976562,
      "A3_mean_abs_angle_error_deg": 2.4234061241149902
    },
    {
      "job_id": "v8_c1diff_full_seed7",
      "candidate_id": "D66_grouped_width320_lr6e-4_dropout0.075_v8c1diff_full_seed7",
      "status": "complete",
      "returncode": 0,
      "elapsed_minutes": 35.45444318874998,
      "selection_score_path": "training_results/model_selection_loop/D66_grouped_width320_lr6e-4_dropout0.075_v8c1diff_full_seed7_20260614_025531_utc/selection_score.json",
      "weighted_score": 0.036933075145531735,
      "rejected": false,
      "true_hard_target_normalized_mae": 0.018571835197508334,
      "hard_label_normalized_mae": 0.018271314248872492,
      "hard_label_normalized_p95": 0.06361424478773887,
      "overall_normalized_mae": 0.014093232341110706,
      "overall_normalized_p95": 0.05266229435801506,
      "easy_target_normalized_mae_relative_change": 0.02002450232326357,
      "C1_mae": 0.8693303465843201,
      "C1_rmse": 1.3780440092086792,
      "C1_p95_abs_error": 2.82616925239563,
      "C1_bias": 0.20145925879478455,
      "C1_normalized_mae": 0.008693303912878036,
      "C1_normalized_p95_abs_error": 0.028261693194508553,
      "validation_normalized_mae": 0.014093232341110706,
      "validation_C1_mae": 1.7945094108581543,
      "validation_C1_rmse": 2.760366439819336,
      "validation_C1_p95_abs_error": 5.762834548950195,
      "validation_C1_bias": 0.29796597361564636,
      "validation_C1_normalized_mae": 0.017945094034075737,
      "validation_C1_normalized_p95_abs_error": 0.05762834474444389,
      "blind_normalized_mae": 0.011424113996326923,
      "blind_C1_mae": 1.2916182279586792,
      "blind_C1_rmse": 2.0383574962615967,
      "blind_C1_p95_abs_error": 4.072114944458008,
      "blind_C1_bias": -0.021556725725531578,
      "blind_C1_normalized_mae": 0.012916182167828083,
      "blind_C1_normalized_p95_abs_error": 0.04072114825248718,
      "stress_normalized_mae": 0.01076529547572136,
      "stress_C1_mae": 1.331478476524353,
      "stress_C1_rmse": 2.7516751289367676,
      "stress_C1_p95_abs_error": 5.009973049163818,
      "stress_C1_bias": 0.22936353087425232,
      "stress_C1_normalized_mae": 0.01331478450447321,
      "stress_C1_normalized_p95_abs_error": 0.050099730491638184,
      "S3_high_magnitude_mae": 5.803321361541748,
      "S3_high_magnitude_bias": -4.541013240814209,
      "S3_high_magnitude_slope": 0.8083499475737017,
      "S3_high_mean_abs_angle_error_deg": 3.3570640087127686,
      "S3_high_p95_abs_angle_error_deg": 10.731555938720703,
      "B2_magnitude_mae": 0.06114514544606209,
      "B2_mean_abs_angle_error_deg": 3.5398619174957275,
      "A3_magnitude_mae": 1.479057788848877,
      "A3_mean_abs_angle_error_deg": 2.4613213539123535
    }
  ],
  "artifact_policy": {
    "push_large_artifacts": false,
    "allowed_artifacts": [
      "run_manifest_model_loop.json",
      "metrics_model_loop.json",
      "selection_score.json",
      "per_target_diagnostics.json",
      "vector_diagnostics.json",
      "s3_magnitude_metric_audit_validation.csv",
      "model_registry_model_loop.csv",
      "training_history_summary.csv",
      "training_history_model_loop.png",
      "prediction_scatter_model_loop.png",
      "batch_manifest.json",
      "batch_summary.csv",
      "c1_feature_sensitivity_*.md",
      "c1_feature_sensitivity_*/*.json",
      "c1_feature_sensitivity_*/*.csv",
      "c1_feature_sensitivity_*/plots/*.png",
      "s3_magnitude_metric_audit_*.md",
      "training_validation_loss_gap_audit_*.md"
    ]
  }
}
